{
    "weeks": [
        {
            "dates": [
                {
                    "date": "2017-02-27", 
                    "weekday": 1, 
                    "events": "\u6625\u5b63\u5b66\u671f\u5f00\u59cb\u4e0a\u8bfe"
                }, 
                {
                    "date": "2017-02-28", 
                    "weekday": 2, 
                    "events": "2017\u6625\u535a\u58eb\u65b0\u751f\u62a5\u5230"
                }, 
                {
                    "date": "2017-03-01", 
                    "weekday": 3, 
                    "events": null
                }, 
                {
                    "date": "2017-03-02", 
                    "weekday": 4, 
                    "events": null
                }, 
                {
                    "date": "2017-03-03", 
                    "weekday": 5, 
                    "events": null
                }, 
                {
                    "date": "2017-03-04", 
                    "weekday": 6, 
                    "events": null
                }, 
                {
                    "date": "2017-03-05", 
                    "weekday": 7, 
                    "events": null
                }
            ], 
            "week_number": 1
        }, 
        {
            "dates": [
                {
                    "date": "2017-03-06", 
                    "weekday": 1, 
                    "events": null
                }, 
                {
                    "date": "2017-03-07", 
                    "weekday": 2, 
                    "events": null
                }, 
                {
                    "date": "2017-03-08", 
                    "weekday": 3, 
                    "events": null
                }, 
                {
                    "date": "2017-03-09", 
                    "weekday": 4, 
                    "events": null
                }, 
                {
                    "date": "2017-03-10", 
                    "weekday": 5, 
                    "events": null
                }, 
                {
                    "date": "2017-03-11", 
                    "weekday": 6, 
                    "events": null
                }, 
                {
                    "date": "2017-03-12", 
                    "weekday": 7, 
                    "events": null
                }
            ], 
            "week_number": 2
        }, 
        {
            "dates": [
                {
                    "date": "2017-03-13", 
                    "weekday": 1, 
                    "events": null
                }, 
                {
                    "date": "2017-03-14", 
                    "weekday": 2, 
                    "events": null
                }, 
                {
                    "date": "2017-03-15", 
                    "weekday": 3, 
                    "events": null
                }, 
                {
                    "date": "2017-03-16", 
                    "weekday": 4, 
                    "events": null
                }, 
                {
                    "date": "2017-03-17", 
                    "weekday": 5, 
                    "events": null
                }, 
                {
                    "date": "2017-03-18", 
                    "weekday": 6, 
                    "events": null
                }, 
                {
                    "date": "2017-03-19", 
                    "weekday": 7, 
                    "events": null
                }
            ], 
            "week_number": 3
        }, 
        {
            "dates": [
                {
                    "date": "2017-03-20", 
                    "weekday": 1, 
                    "events": null
                }, 
                {
                    "date": "2017-03-21", 
                    "weekday": 2, 
                    "events": null
                }, 
                {
                    "date": "2017-03-22", 
                    "weekday": 3, 
                    "events": null
                }, 
                {
                    "date": "2017-03-23", 
                    "weekday": 4, 
                    "events": null
                }, 
                {
                    "date": "2017-03-24", 
                    "weekday": 5, 
                    "events": null
                }, 
                {
                    "date": "2017-03-25", 
                    "weekday": 6, 
                    "events": null
                }, 
                {
                    "date": "2017-03-26", 
                    "weekday": 7, 
                    "events": null
                }
            ], 
            "week_number": 4
        }, 
        {
            "dates": [
                {
                    "date": "2017-03-27", 
                    "weekday": 1, 
                    "events": null
                }, 
                {
                    "date": "2017-03-28", 
                    "weekday": 2, 
                    "events": null
                }, 
                {
                    "date": "2017-03-29", 
                    "weekday": 3, 
                    "events": null
                }, 
                {
                    "date": "2017-03-30", 
                    "weekday": 4, 
                    "events": null
                }, 
                {
                    "date": "2017-03-31", 
                    "weekday": 5, 
                    "events": null
                }, 
                {
                    "date": "2017-04-01", 
                    "weekday": 6, 
                    "events": null
                }, 
                {
                    "date": "2017-04-02", 
                    "weekday": 7, 
                    "events": "\u6e05\u660e\u8282\u653e\u5047\u8c03\u4f113\u5929"
                }
            ], 
            "week_number": 5
        }, 
        {
            "dates": [
                {
                    "date": "2017-04-03", 
                    "weekday": 1, 
                    "events": "\u6e05\u660e\u8282\u653e\u5047\u8c03\u4f113\u5929"
                }, 
                {
                    "date": "2017-04-04", 
                    "weekday": 2, 
                    "events": "\u6e05\u660e\u8282\u653e\u5047\u8c03\u4f113\u5929"
                }, 
                {
                    "date": "2017-04-05", 
                    "weekday": 3, 
                    "events": null
                }, 
                {
                    "date": "2017-04-06", 
                    "weekday": 4, 
                    "events": null
                }, 
                {
                    "date": "2017-04-07", 
                    "weekday": 5, 
                    "events": null
                }, 
                {
                    "date": "2017-04-08", 
                    "weekday": 6, 
                    "events": null
                }, 
                {
                    "date": "2017-04-09", 
                    "weekday": 7, 
                    "events": null
                }
            ], 
            "week_number": 6
        }, 
        {
            "dates": [
                {
                    "date": "2017-04-10", 
                    "weekday": 1, 
                    "events": null
                }, 
                {
                    "date": "2017-04-11", 
                    "weekday": 2, 
                    "events": null
                }, 
                {
                    "date": "2017-04-12", 
                    "weekday": 3, 
                    "events": null
                }, 
                {
                    "date": "2017-04-13", 
                    "weekday": 4, 
                    "events": null
                }, 
                {
                    "date": "2017-04-14", 
                    "weekday": 5, 
                    "events": null
                }, 
                {
                    "date": "2017-04-15", 
                    "weekday": 6, 
                    "events": null
                }, 
                {
                    "date": "2017-04-16", 
                    "weekday": 7, 
                    "events": null
                }
            ], 
            "week_number": 7
        }, 
        {
            "dates": [
                {
                    "date": "2017-04-17", 
                    "weekday": 1, 
                    "events": null
                }, 
                {
                    "date": "2017-04-18", 
                    "weekday": 2, 
                    "events": null
                }, 
                {
                    "date": "2017-04-19", 
                    "weekday": 3, 
                    "events": null
                }, 
                {
                    "date": "2017-04-20", 
                    "weekday": 4, 
                    "events": null
                }, 
                {
                    "date": "2017-04-21", 
                    "weekday": 5, 
                    "events": null
                }, 
                {
                    "date": "2017-04-22", 
                    "weekday": 6, 
                    "events": null
                }, 
                {
                    "date": "2017-04-23", 
                    "weekday": 7, 
                    "events": null
                }
            ], 
            "week_number": 8
        }, 
        {
            "dates": [
                {
                    "date": "2017-04-24", 
                    "weekday": 1, 
                    "events": null
                }, 
                {
                    "date": "2017-04-25", 
                    "weekday": 2, 
                    "events": null
                }, 
                {
                    "date": "2017-04-26", 
                    "weekday": 3, 
                    "events": null
                }, 
                {
                    "date": "2017-04-27", 
                    "weekday": 4, 
                    "events": null
                }, 
                {
                    "date": "2017-04-28", 
                    "weekday": 5, 
                    "events": null
                }, 
                {
                    "date": "2017-04-29", 
                    "weekday": 6, 
                    "events": "\u52b3\u52a8\u8282\u653e\u50473\u5929"
                }, 
                {
                    "date": "2017-04-30", 
                    "weekday": 7, 
                    "events": "\u52b3\u52a8\u8282\u653e\u50473\u5929"
                }
            ], 
            "week_number": 9
        }, 
        {
            "dates": [
                {
                    "date": "2017-05-01", 
                    "weekday": 1, 
                    "events": "\u52b3\u52a8\u8282\u653e\u50473\u5929"
                }, 
                {
                    "date": "2017-05-02", 
                    "weekday": 2, 
                    "events": null
                }, 
                {
                    "date": "2017-05-03", 
                    "weekday": 3, 
                    "events": null
                }, 
                {
                    "date": "2017-05-04", 
                    "weekday": 4, 
                    "events": null
                }, 
                {
                    "date": "2017-05-05", 
                    "weekday": 5, 
                    "events": null
                }, 
                {
                    "date": "2017-05-06", 
                    "weekday": 6, 
                    "events": null
                }, 
                {
                    "date": "2017-05-07", 
                    "weekday": 7, 
                    "events": null
                }
            ], 
            "week_number": 10
        }, 
        {
            "dates": [
                {
                    "date": "2017-05-08", 
                    "weekday": 1, 
                    "events": null
                }, 
                {
                    "date": "2017-05-09", 
                    "weekday": 2, 
                    "events": null
                }, 
                {
                    "date": "2017-05-10", 
                    "weekday": 3, 
                    "events": null
                }, 
                {
                    "date": "2017-05-11", 
                    "weekday": 4, 
                    "events": null
                }, 
                {
                    "date": "2017-05-12", 
                    "weekday": 5, 
                    "events": null
                }, 
                {
                    "date": "2017-05-13", 
                    "weekday": 6, 
                    "events": null
                }, 
                {
                    "date": "2017-05-14", 
                    "weekday": 7, 
                    "events": null
                }
            ], 
            "week_number": 11
        }, 
        {
            "dates": [
                {
                    "date": "2017-05-15", 
                    "weekday": 1, 
                    "events": null
                }, 
                {
                    "date": "2017-05-16", 
                    "weekday": 2, 
                    "events": null
                }, 
                {
                    "date": "2017-05-17", 
                    "weekday": 3, 
                    "events": null
                }, 
                {
                    "date": "2017-05-18", 
                    "weekday": 4, 
                    "events": null
                }, 
                {
                    "date": "2017-05-19", 
                    "weekday": 5, 
                    "events": null
                }, 
                {
                    "date": "2017-05-20", 
                    "weekday": 6, 
                    "events": null
                }, 
                {
                    "date": "2017-05-21", 
                    "weekday": 7, 
                    "events": null
                }
            ], 
            "week_number": 12
        }, 
        {
            "dates": [
                {
                    "date": "2017-05-22", 
                    "weekday": 1, 
                    "events": null
                }, 
                {
                    "date": "2017-05-23", 
                    "weekday": 2, 
                    "events": null
                }, 
                {
                    "date": "2017-05-24", 
                    "weekday": 3, 
                    "events": null
                }, 
                {
                    "date": "2017-05-25", 
                    "weekday": 4, 
                    "events": null
                }, 
                {
                    "date": "2017-05-26", 
                    "weekday": 5, 
                    "events": "\u6821\u8fd0\u52a8\u4f1a"
                }, 
                {
                    "date": "2017-05-27", 
                    "weekday": 6, 
                    "events": "\u6821\u8fd0\u52a8\u4f1a"
                }, 
                {
                    "date": "2017-05-28", 
                    "weekday": 7, 
                    "events": "\u7aef\u5348\u8282\u653e\u5047\u8c03\u4f113\u5929"
                }
            ], 
            "week_number": 13
        }, 
        {
            "dates": [
                {
                    "date": "2017-05-29", 
                    "weekday": 1, 
                    "events": "\u7aef\u5348\u8282\u653e\u5047\u8c03\u4f113\u5929"
                }, 
                {
                    "date": "2017-05-30", 
                    "weekday": 2, 
                    "events": "\u7aef\u5348\u8282\u653e\u5047\u8c03\u4f113\u5929"
                }, 
                {
                    "date": "2017-05-31", 
                    "weekday": 3, 
                    "events": null
                }, 
                {
                    "date": "2017-06-01", 
                    "weekday": 4, 
                    "events": null
                }, 
                {
                    "date": "2017-06-02", 
                    "weekday": 5, 
                    "events": null
                }, 
                {
                    "date": "2017-06-03", 
                    "weekday": 6, 
                    "events": null
                }, 
                {
                    "date": "2017-06-04", 
                    "weekday": 7, 
                    "events": null
                }
            ], 
            "week_number": 14
        }, 
        {
            "dates": [
                {
                    "date": "2017-06-05", 
                    "weekday": 1, 
                    "events": null
                }, 
                {
                    "date": "2017-06-06", 
                    "weekday": 2, 
                    "events": null
                }, 
                {
                    "date": "2017-06-07", 
                    "weekday": 3, 
                    "events": null
                }, 
                {
                    "date": "2017-06-08", 
                    "weekday": 4, 
                    "events": null
                }, 
                {
                    "date": "2017-06-09", 
                    "weekday": 5, 
                    "events": null
                }, 
                {
                    "date": "2017-06-10", 
                    "weekday": 6, 
                    "events": null
                }, 
                {
                    "date": "2017-06-11", 
                    "weekday": 7, 
                    "events": null
                }
            ], 
            "week_number": 15
        }, 
        {
            "dates": [
                {
                    "date": "2017-06-12", 
                    "weekday": 1, 
                    "events": null
                }, 
                {
                    "date": "2017-06-13", 
                    "weekday": 2, 
                    "events": null
                }, 
                {
                    "date": "2017-06-14", 
                    "weekday": 3, 
                    "events": null
                }, 
                {
                    "date": "2017-06-15", 
                    "weekday": 4, 
                    "events": null
                }, 
                {
                    "date": "2017-06-16", 
                    "weekday": 5, 
                    "events": null
                }, 
                {
                    "date": "2017-06-17", 
                    "weekday": 6, 
                    "events": null
                }, 
                {
                    "date": "2017-06-18", 
                    "weekday": 7, 
                    "events": null
                }
            ], 
            "week_number": 16
        }, 
        {
            "dates": [
                {
                    "date": "2017-06-19", 
                    "weekday": 1, 
                    "events": null
                }, 
                {
                    "date": "2017-06-20", 
                    "weekday": 2, 
                    "events": null
                }, 
                {
                    "date": "2017-06-21", 
                    "weekday": 3, 
                    "events": null
                }, 
                {
                    "date": "2017-06-22", 
                    "weekday": 4, 
                    "events": null
                }, 
                {
                    "date": "2017-06-23", 
                    "weekday": 5, 
                    "events": null
                }, 
                {
                    "date": "2017-06-24", 
                    "weekday": 6, 
                    "events": null
                }, 
                {
                    "date": "2017-06-25", 
                    "weekday": 7, 
                    "events": null
                }
            ], 
            "week_number": 17
        }, 
        {
            "dates": [
                {
                    "date": "2017-06-26", 
                    "weekday": 1, 
                    "events": "\u671f\u672b\u8003\u8bd5"
                }, 
                {
                    "date": "2017-06-27", 
                    "weekday": 2, 
                    "events": "\u671f\u672b\u8003\u8bd5"
                }, 
                {
                    "date": "2017-06-28", 
                    "weekday": 3, 
                    "events": "\u671f\u672b\u8003\u8bd5"
                }, 
                {
                    "date": "2017-06-29", 
                    "weekday": 4, 
                    "events": "\u671f\u672b\u8003\u8bd5"
                }, 
                {
                    "date": "2017-06-30", 
                    "weekday": 5, 
                    "events": "\u671f\u672b\u8003\u8bd5"
                }, 
                {
                    "date": "2017-07-01", 
                    "weekday": 6, 
                    "events": null
                }, 
                {
                    "date": "2017-07-02", 
                    "weekday": 7, 
                    "events": null
                }
            ], 
            "week_number": 18
        }
    ]
}